openspace/__init__.py
openspace/messages.py
openspace/time.py
openspace/bodies/__init__.py
openspace/bodies/artificial.py
openspace/bodies/celestial.py
openspace/bodies/terrestrial.py
openspace/coordinates/__init__.py
openspace/coordinates/elements.py
openspace/coordinates/positions.py
openspace/coordinates/states.py
openspace/data/__init__.py
openspace/data/live.py
openspace/estimation/__init__.py
openspace/estimation/filtering.py
openspace/estimation/iod.py
openspace/estimation/obs.py
openspace/hardware/__init__.py
openspace/hardware/constraints.py
openspace/hardware/payloads.py
openspace/math/__init__.py
openspace/math/constants.py
openspace/math/functions.py
openspace/math/linalg.py
openspace/planning/__init__.py
openspace/planning/maneuvers.py
openspace/propagators/__init__.py
openspace/propagators/inertial.py
openspace/propagators/relative.py
openspace-2.6.1.dist-info/LICENSE
openspace-2.6.1.dist-info/METADATA
openspace-2.6.1.dist-info/WHEEL
openspace-2.6.1.dist-info/top_level.txt
openspace-2.6.1.dist-info/RECORD
