Metadata-Version: 2.1
Name: openspace
Version: 2.6.1
Summary: astrodynamics analysis and simulation package
Author-email: Brandon Sexton <brandon.sexton.1@outlook.com>
License: GNU GENERAL PUBLIC LICENSE
Project-URL: Documentation, https://www.openspace-docs.com/
Project-URL: Application, https://www.openspace-app.com/
Project-URL: App Repository, https://github.com/brandon-sexton/openspace-app
Project-URL: Backend Repository, https://github.com/brandon-sexton/openspace
Requires-Python: >=3.8
License-File: LICENSE
Requires-Dist: requests
Requires-Dist: matplotlib
Provides-Extra: dev
Requires-Dist: poetry ; extra == 'dev'
Requires-Dist: black ; extra == 'dev'
Requires-Dist: pre-commit ; extra == 'dev'
Requires-Dist: isort ; extra == 'dev'
Requires-Dist: mypy ; extra == 'dev'
Requires-Dist: flake8 ; extra == 'dev'
